{
  "name": "actuator_saturation",
  "dt": 0.025,
  "duration": 14.0,
  "vehicle_config": "../vehicles/baseline.json",
  "environment_config": "../environments/calm.json",
  "initial": {
    "position_m": [0.0, 0.0, 1000.0],
    "velocity_mps": [92.0, 0.0, 14.0],
    "euler_deg": [0.0, 8.0, 0.0]
  },
  "vehicle": {
    "actuators": {
      "surface_limit_deg": 10.0,
      "surface_rate_dps": 70.0
    }
  },
  "guidance": {
    "mode": "fixed_pitch",
    "pitch_command_deg": 26.0,
    "heading_command_deg": 12.0,
    "throttle": 0.9
  },
  "events": {
    "qbar_limit_pa": 85000.0,
    "load_limit_g": 10.0
  },
  "sensors": {
    "seed": 101
  }
}
